meds_torch/__init__.py
meds_torch/eval.py
meds_torch/finetune.py
meds_torch/generate_trajectories.py
meds_torch/latest_dir.py
meds_torch/predict.py
meds_torch/train.py
meds_torch/tune.py
meds_torch/configs/__init__.py
meds_torch/configs/eval.yaml
meds_torch/configs/finetune.yaml
meds_torch/configs/generate_trajectories.yaml
meds_torch/configs/latest_dir.yaml
meds_torch/configs/predict.yaml
meds_torch/configs/train.yaml
meds_torch/configs/callbacks/__init__.py
meds_torch/configs/callbacks/default.yaml
meds_torch/configs/callbacks/early_stopping.yaml
meds_torch/configs/callbacks/model_checkpoint.yaml
meds_torch/configs/callbacks/model_summary.yaml
meds_torch/configs/callbacks/none.yaml
meds_torch/configs/callbacks/ray.yaml
meds_torch/configs/callbacks/rich_progress_bar.yaml
meds_torch/configs/callbacks/tune_default.yaml
meds_torch/configs/data/__init__.py
meds_torch/configs/data/multiwindow_pytorch_dataset.yaml
meds_torch/configs/data/pytorch_dataset.yaml
meds_torch/configs/data/random_windows_pytorch_dataset.yaml
meds_torch/configs/debug/__init__.py
meds_torch/configs/debug/default.yaml
meds_torch/configs/debug/fdr.yaml
meds_torch/configs/debug/limit.yaml
meds_torch/configs/debug/overfit.yaml
meds_torch/configs/debug/profiler.yaml
meds_torch/configs/experiment/__init__.py
meds_torch/configs/experiment/example.yaml
meds_torch/configs/experiment/mimiciv.yaml
meds_torch/configs/extras/__init__.py
meds_torch/configs/extras/default.yaml
meds_torch/configs/hparams_search/__init__.py
meds_torch/configs/hparams_search/optuna.yaml
meds_torch/configs/hparams_search/ray_multiseed.yaml
meds_torch/configs/hparams_search/ray_tune.yaml
meds_torch/configs/hydra/__init__.py
meds_torch/configs/hydra/default.yaml
meds_torch/configs/logger/__init__.py
meds_torch/configs/logger/aim.yaml
meds_torch/configs/logger/comet.yaml
meds_torch/configs/logger/csv.yaml
meds_torch/configs/logger/many_loggers.yaml
meds_torch/configs/logger/mlflow.yaml
meds_torch/configs/logger/neptune.yaml
meds_torch-0.0.8.dist-info/LICENSE
meds_torch-0.0.8.dist-info/METADATA
meds_torch-0.0.8.dist-info/WHEEL
meds_torch-0.0.8.dist-info/entry_points.txt
meds_torch-0.0.8.dist-info/top_level.txt
meds_torch-0.0.8.dist-info/RECORD
