Metadata-Version: 2.1
Name: meds-torch
Version: 0.0.8
Summary: A MEDS PyTorch Dataset, leveraging a on-the-fly retrieval strategy for flexible, efficient data loading.
Author-email: Matthew McDermott <mattmcdermott8@gmail.com>, Nassim Oufattole <noufattole@gmail.com>, Teya Bergamaschi <teyabergamaschi@gmail.com>, Aleksia Kolo <aleksiakolo@gmail.com>
Project-URL: Homepage, https://github.com/oufattole/meds-torch
Project-URL: Issues, https://github.com/oufattole/meds-torch/issues
Classifier: Programming Language :: Python :: 3
Classifier: License :: OSI Approved :: MIT License
Classifier: Operating System :: OS Independent
Requires-Python: >=3.11
License-File: LICENSE
Requires-Dist: polars
Requires-Dist: pyarrow
Requires-Dist: nested_ragged_tensors>=0.1.0
Requires-Dist: loguru
Requires-Dist: numpy
Requires-Dist: ml-mixins
Requires-Dist: torch
Requires-Dist: omegaconf
Requires-Dist: hydra-core
Requires-Dist: lightning
Requires-Dist: x-transformers==1.34.0
Requires-Dist: rich
Requires-Dist: hydra-colorlog
Requires-Dist: hydra-optuna-sweeper
Requires-Dist: wandb
Requires-Dist: torchmetrics
Requires-Dist: torchvision
Requires-Dist: transformers
Requires-Dist: ray[tune]
Requires-Dist: clinical-zeroshot-labeler==0.0.3
Requires-Dist: lightning-bolts
Provides-Extra: dev
Requires-Dist: pre-commit<4; extra == "dev"
Requires-Dist: notebook; extra == "dev"
Requires-Dist: pdbpp; extra == "dev"
Provides-Extra: tests
Requires-Dist: pytest; extra == "tests"
Requires-Dist: pytest-cov[toml]; extra == "tests"
Requires-Dist: rootutils; extra == "tests"
Requires-Dist: pytest-xdist; extra == "tests"
Requires-Dist: sh; extra == "tests"
Requires-Dist: MEDS-transforms>=0.0.9; extra == "tests"
Requires-Dist: pytest-loguru; extra == "tests"
Provides-Extra: docs
Requires-Dist: mkdocs==1.6.0; extra == "docs"
Requires-Dist: mkdocs-gen-files==0.5.0; extra == "docs"
Requires-Dist: mkdocs-get-deps==0.2.0; extra == "docs"
Requires-Dist: mkdocs-git-authors-plugin==0.9.0; extra == "docs"
Requires-Dist: mkdocs-git-revision-date-localized-plugin==1.2.7; extra == "docs"
Requires-Dist: mkdocs-literate-nav==0.6.1; extra == "docs"
Requires-Dist: mkdocs-material==9.5.33; extra == "docs"
Requires-Dist: mkdocs-material-extensions==1.3.1; extra == "docs"
Requires-Dist: mkdocs-section-index==0.3.9; extra == "docs"
Requires-Dist: mkdocs-snippets==1.3.0; extra == "docs"
Requires-Dist: mkdocstrings==0.25.2; extra == "docs"
Requires-Dist: mkdocstrings-python==1.10.8; extra == "docs"
